{"id":18816,"name":"Bloemkolk, Willem/Wisselingh & Co., E.J. van aan Witsen, Willem Arnoldus | 1913-06-24","paralleltexts":{"Transcription":{"text":"24 Juni 1913<br><br>Geachte Heer Witsen,<br>Naar aanleiding van Uw geacht schrijven deelen wij U mede dat de ‘schuiten i.d. Oude Schans’ naar Gent gezonden is. Hierbij een lijstje van 't geen op 't oogenblik van U in huis is, wilt U daaruit iets kiezen dan kunt U desnoods telegrafisch opgeven wat ge wenscht dat we zullen zenden.<br>De andere schilderijen zijn gisteren verzonden, dus zijn nu wel aangekomen. Wij schreven den Secretaris over de assurantie. Dat wij schilderijen afstaan, doen wij meer ter opluistering van de tentoonstelling dan omdat wij er eenig belang voor ons inzien. Daarom zou het ons inziens onbillijk zijn indien wij ook nog kosten voor verzekering zouden hebben. Wilt U dit Uw mede bestuursleden s.v.p. eens duidelijk maken.<br><br>Met beste groeten<br>EJ van <i>Wisselingh &amp; C<sup>o</sup></i>.<br>","annotationData":[]}},"shortName":"1913-06-24","facsimiles":[],"metadata":[{"field":"Afzender(s)","value":"Bloemkolk, Willem"},{"field":"Ontvanger(s)","value":"Witsen, Willem Arnoldus"},{"field":"Plaats","value":"Amsterdam"},{"field":"Datum","value":"1913-06-24"},{"field":"Annotatie","value":"Afzender: Willem Bloemkolk (SWW). Scan(s) niet beschikbaar"},{"field":"Taal","value":"Nederlands"},{"field":"Bijlage(n)","value":""},{"field":"Transcriptie","value":"Kritisch"},{"field":"Herkomst transcriptie","value":"SWW"},{"field":"Bewaarplaats","value":"Rijksbureau voor Kunsthistorische Documentatie, Den Haag"},{"field":"Collectie","value":"Archief Van Wisselingh & Co."},{"field":"Signatuur","value":"inv.nr. 47, p. 43"}]}