{"id":23600,"name":"Opzoomer, Adèle Sophia Cordelia aan Verwey, Albert | 1886-07-02","paralleltexts":{"Transcription":{"text":"<b>¶</b>Velp. 2 Juli<br> <br>Waarde Heer!<br>De Utrechtsche feestdrukte is voorbij, en ik bevind mij in 't rustige Velp, waar zomergroen en zonneschijn 't nu recht bekoorlijk maken. Ik schreef u, dat ik van hieruit uw brief spoedig zou beantwoorden, en ik maak dus van dit stille morgenuurtje gebruik, om aan mijn verzekering te voldoen.<br>De vragen, die gij in uw brief aanroert, hebben mij even als u reeds lang ernstig bezig gehouden, en er is veel in uw opmerkingen, ik heb ook uw stuk in het laatste N.G. Nr. op't oog, waarmee ik gaarne instem. Toch kan ik niet geheel met u mee gaan, waar gij spreekt over 't ongeoorloofd gebruik maken van ‘woordcombinaties, zeggingswijzen, beeldspraak enz’, die<b> ¶</b>reeds lang ook door anderen gebezigd zijn. Ik stem u toe, dat de aangehaalde plaats uit Mev. B. Wonderdokter niet gelukkig is, ik vind die overdenkingen gerekt en ook niet bijzonder wel aangebracht, maar dat zij zich van uitdrukkingen bedient, als die gij onderschrapt:<br>‘lokte die stad uit om zich in feesttooi te dossen -<br>‘de heugelijke nieuwsmare van deze ongewachte uitkomst... enz’ <br>hierin kan ik niets laakbaars vinden. Er is hier immers geen sprake van ‘'t weergeven der bewegingen van onze ziel.’ Zoodra het uitingen van gevoel geldt, mag geen schrijver conventioneel zijn, dat ben ik met u eens, ja, ik ga nog verder en zeg: geen schrijver, die waarachtig kunstenaar is, <i>kan</i> daar conventioneel zijn. Maar iedere roman heeft zijn bladzijden, die als 't ware<b> ¶</b>tot voorbereiding, ook wel tot rustpunt dienen, en waarin uit den aard der zaak, niets bijzonders kan worden gezegd. Vindt gij nu, dat men zich om iets uiterst gewoons te zeggen, niet ook bedienen mag van de gewone woorden, die elk dadelijk begrijpt, en die het bewijs van hun juist zijn in hun algemeen zijn bezitten? Niemand zal bij een uitdrukking als ‘lokte die stad uit om zich in feesttooi te dossen,’ twijfelend vragen: wat is hier bedoeld? Hij heeft een feit, waaraan geen gewicht is verbonden, terloops vernomen; een zinsnede vol eigenaardige ‘woordvondsten’ zou den lezer daarbij doen stilstaan, en ik geloof dat noch schrijver, noch publiek deze vermoeienis van hersenen op den duur zouden kunnen uithouden, dat zij eindelijk het wezenlijke en onwezenlijke, of liever, want<b> ¶</b>onwezenlijk is miskenning van 't belang der détails, en daaraan wil ik mij niet gaarne schuldig maken, dat zij dus hoofd en bijwerk met elkander zouden gaan verwarren. Gij kent zeker Macaulay's stuk over Madame d'Arblay, vindt gij zijn opmerkingen over haar latere schrijfwijze, toen zij alles mooi en bijzonder wilde gaan zeggen, niet treffend? Ik geloof dat gij, als dichter sprekend, gelijk hebt, wanneer gij in de Lyriek - die gevoelsuiting bij uitnemendheid - het gebruikmaken van door anderen reeds gebezigde vormen ten strengste afkeurt, daar is het de eigen ziel, die moet  spreken, maar de romanschrijver, hij die zooveel bladzijden moet schrijven, kan hij in al die duizendtallen van regels steeds iets zeggen dat nieuw, opmerkelijk, ongewoon van taal is?<b> ¶</b>Ik acht zulks niet alleen onmogelijk, maar ook onwenschelijk. Groote virtuositeit in 't maken van nieuwe woorden is zeker een te waardeeren talent, maar loopt het niet gevaar in een spelen daarmee, in een gedachtenloos klanken vormen te ontaarden? Is het niet opmerkelijk dat Shakespeare gezegd wordt een der dichters te zijn, die de <i>minste</i> verscheidenheid van woorden gebruikte? - Ik weet niet hoe de roman, waarvan gij in uw stuk spreekt, de roman, die in het weergeven van sensaties zou bestaan, zal wezen, en 't is zeer wel mogelijk, dat die mijn oordeel geheel wijzigen zou, maar ik kan mij dien nu alleen voorstellen als iets, wat mij in verwarring brengt, een opeenstapeling van beelden, zooals ik<b> ¶</b>die in Netscher's herfstelijk woud vond, waar zooveel vergelijkingen zijn, dat ik ten slotte geen enkel beeld meer voor mij zag, het eene wischte het andere uit. - Gij onderscheidt kunst van waarneming, stemmingskunst en kunst van weergeven onzer sensaties, mij dunkt dat alleen de vereeniging dier eigenschappen volmaakte kunst zou mogen heeten, en dat ze aanwezig zijn in de beste werken van alle volken. Feith's Julia is zoo weinig origineel dat het haast niet als proeve gelden kan, naar mij dunkt, ware het echter oorspronkelijk, dan zou 't inderdaad zuiver stemmingswerk zijn, maar is in Werther niet even veel waarneming - waarneming van den tijd, van pas gebeurde feiten - als stemming? En zou niet ook hierin<b> ¶</b>voor een deel zijn meerderheid boven de andere werken uit die periode gelezen zijn? Ik vind dat van al de werken van Mev. B. ‘het huis Lauernesse’ en ‘de Wonderdokter’ meest bezield en meest ‘lebenswahr’ zijn, zou dit niet ook daarin zijn verklaring vinden, dat b.v.b. Paul en de Wonderdokter trekken van bekende personen moeten dragen, dus naast stemming ook waarneming zijn? -<br>Maar ik merk, dat mijn brief erg lang zou gaan worden, en dat ik dus aan 't woord: eindigen moet denken. Ik heb 't In Memoriam van Mev. B., nu zich dat tot een kort woord moet beperken, met instemming gelezen. Het beantwoorden van uw brief bracht met zich, dat ik soms van<b> ¶</b>u verschilde, dit sluit niet uit, dat ik uw stuk met genoegen las, en met veel belangstelling het vervolg tegemoet zie; ik vond in het meegedeelde veel, dat mij tot overdenken stemde.<br>Zoo gij tijd hebt mij eens te schrijven, mijn adres is: Mej. H. Kolff. Velp (bij Arnhem.)<br>Met vriendschappelijken groet noem ik mij:<br>Uw dw.<br>Adèle Opzoomer.<br>¶<br>¶<br>","annotationData":[]}},"shortName":"1886-07-02","facsimiles":[{"title":"01: Blad 1","thumbnail":"https://tomcat.tiler01.huygens.knaw.nl/adore-djatoka/resolver?url_ver=Z39.88-2004&svc_id=info:lanl-repo/svc/getRegion&svc_val_fmt=info:ofi/fmt:kev:mtx:jpeg2000&svc.format=image/jpeg&svc.level=1&rft_id=http://localhost:8080/jp2/verwey/UBAHSXLIB9/UBAHSXLIB9863_0003.jp2","zoom":"https://tomcat.tiler01.huygens.knaw.nl/adore-djatoka/viewer2.1.html?rft_id=http://localhost:8080/jp2/verwey/UBAHSXLIB9/UBAHSXLIB9863_0003.jp2"},{"title":"02: Blad 2","thumbnail":"https://tomcat.tiler01.huygens.knaw.nl/adore-djatoka/resolver?url_ver=Z39.88-2004&svc_id=info:lanl-repo/svc/getRegion&svc_val_fmt=info:ofi/fmt:kev:mtx:jpeg2000&svc.format=image/jpeg&svc.level=1&rft_id=http://localhost:8080/jp2/verwey/UBAHSXLIB9/UBAHSXLIB9863_0004.jp2","zoom":"https://tomcat.tiler01.huygens.knaw.nl/adore-djatoka/viewer2.1.html?rft_id=http://localhost:8080/jp2/verwey/UBAHSXLIB9/UBAHSXLIB9863_0004.jp2"},{"title":"03: Blad 3","thumbnail":"https://tomcat.tiler01.huygens.knaw.nl/adore-djatoka/resolver?url_ver=Z39.88-2004&svc_id=info:lanl-repo/svc/getRegion&svc_val_fmt=info:ofi/fmt:kev:mtx:jpeg2000&svc.format=image/jpeg&svc.level=1&rft_id=http://localhost:8080/jp2/verwey/UBAHSXLIB9/UBAHSXLIB9863_0005.jp2","zoom":"https://tomcat.tiler01.huygens.knaw.nl/adore-djatoka/viewer2.1.html?rft_id=http://localhost:8080/jp2/verwey/UBAHSXLIB9/UBAHSXLIB9863_0005.jp2"},{"title":"04: Blad 4","thumbnail":"https://tomcat.tiler01.huygens.knaw.nl/adore-djatoka/resolver?url_ver=Z39.88-2004&svc_id=info:lanl-repo/svc/getRegion&svc_val_fmt=info:ofi/fmt:kev:mtx:jpeg2000&svc.format=image/jpeg&svc.level=1&rft_id=http://localhost:8080/jp2/verwey/UBAHSXLIB9/UBAHSXLIB9863_0006.jp2","zoom":"https://tomcat.tiler01.huygens.knaw.nl/adore-djatoka/viewer2.1.html?rft_id=http://localhost:8080/jp2/verwey/UBAHSXLIB9/UBAHSXLIB9863_0006.jp2"},{"title":"05: Blad 5","thumbnail":"https://tomcat.tiler01.huygens.knaw.nl/adore-djatoka/resolver?url_ver=Z39.88-2004&svc_id=info:lanl-repo/svc/getRegion&svc_val_fmt=info:ofi/fmt:kev:mtx:jpeg2000&svc.format=image/jpeg&svc.level=1&rft_id=http://localhost:8080/jp2/verwey/UBAHSXLIB9/UBAHSXLIB9863_0007.jp2","zoom":"https://tomcat.tiler01.huygens.knaw.nl/adore-djatoka/viewer2.1.html?rft_id=http://localhost:8080/jp2/verwey/UBAHSXLIB9/UBAHSXLIB9863_0007.jp2"},{"title":"06: Blad 6","thumbnail":"https://tomcat.tiler01.huygens.knaw.nl/adore-djatoka/resolver?url_ver=Z39.88-2004&svc_id=info:lanl-repo/svc/getRegion&svc_val_fmt=info:ofi/fmt:kev:mtx:jpeg2000&svc.format=image/jpeg&svc.level=1&rft_id=http://localhost:8080/jp2/verwey/UBAHSXLIB9/UBAHSXLIB9863_0008.jp2","zoom":"https://tomcat.tiler01.huygens.knaw.nl/adore-djatoka/viewer2.1.html?rft_id=http://localhost:8080/jp2/verwey/UBAHSXLIB9/UBAHSXLIB9863_0008.jp2"},{"title":"07: Blad 7","thumbnail":"https://tomcat.tiler01.huygens.knaw.nl/adore-djatoka/resolver?url_ver=Z39.88-2004&svc_id=info:lanl-repo/svc/getRegion&svc_val_fmt=info:ofi/fmt:kev:mtx:jpeg2000&svc.format=image/jpeg&svc.level=1&rft_id=http://localhost:8080/jp2/verwey/UBAHSXLIB9/UBAHSXLIB9863_0009.jp2","zoom":"https://tomcat.tiler01.huygens.knaw.nl/adore-djatoka/viewer2.1.html?rft_id=http://localhost:8080/jp2/verwey/UBAHSXLIB9/UBAHSXLIB9863_0009.jp2"},{"title":"08: Blad 8","thumbnail":"https://tomcat.tiler01.huygens.knaw.nl/adore-djatoka/resolver?url_ver=Z39.88-2004&svc_id=info:lanl-repo/svc/getRegion&svc_val_fmt=info:ofi/fmt:kev:mtx:jpeg2000&svc.format=image/jpeg&svc.level=1&rft_id=http://localhost:8080/jp2/verwey/UBAHSXLIB9/UBAHSXLIB9863_0010.jp2","zoom":"https://tomcat.tiler01.huygens.knaw.nl/adore-djatoka/viewer2.1.html?rft_id=http://localhost:8080/jp2/verwey/UBAHSXLIB9/UBAHSXLIB9863_0010.jp2"},{"title":"09: Envelop voorzijde","thumbnail":"https://tomcat.tiler01.huygens.knaw.nl/adore-djatoka/resolver?url_ver=Z39.88-2004&svc_id=info:lanl-repo/svc/getRegion&svc_val_fmt=info:ofi/fmt:kev:mtx:jpeg2000&svc.format=image/jpeg&svc.level=1&rft_id=http://localhost:8080/jp2/verwey/UBAHSXLIB9/UBAHSXLIB9863_0001.jp2","zoom":"https://tomcat.tiler01.huygens.knaw.nl/adore-djatoka/viewer2.1.html?rft_id=http://localhost:8080/jp2/verwey/UBAHSXLIB9/UBAHSXLIB9863_0001.jp2"},{"title":"10: Envelop achterzijde","thumbnail":"https://tomcat.tiler01.huygens.knaw.nl/adore-djatoka/resolver?url_ver=Z39.88-2004&svc_id=info:lanl-repo/svc/getRegion&svc_val_fmt=info:ofi/fmt:kev:mtx:jpeg2000&svc.format=image/jpeg&svc.level=1&rft_id=http://localhost:8080/jp2/verwey/UBAHSXLIB9/UBAHSXLIB9863_0002.jp2","zoom":"https://tomcat.tiler01.huygens.knaw.nl/adore-djatoka/viewer2.1.html?rft_id=http://localhost:8080/jp2/verwey/UBAHSXLIB9/UBAHSXLIB9863_0002.jp2"}],"metadata":[{"field":"Afzender(s)","value":"Opzoomer, Adèle Sophia Cordelia"},{"field":"Ontvanger(s)","value":"Verwey, Albert"},{"field":"Plaats","value":"Velp"},{"field":"Datum","value":"1886-07-02"},{"field":"Annotatie","value":"Jaartal ontleend aan poststempel envelop (OPC)"},{"field":"Taal","value":"Nederlands"},{"field":"Bijlage(n)","value":""},{"field":"Transcriptie","value":"Kritisch"},{"field":"Herkomst transcriptie","value":"S&vdW"},{"field":"Bewaarplaats","value":"Bijzondere Collecties UvA, Amsterdam"},{"field":"Collectie","value":"Collectie Albert Verwey"},{"field":"Signatuur","value":"XLI B 9863"}]}